pypika/__init__.py
pypika/analytics.py
pypika/dialects.py
pypika/enums.py
pypika/functions.py
pypika/mixins.py
pypika/pseudocolumns.py
pypika/py.typed
pypika/queries.py
pypika/terms.py
pypika/utils.py
pypika/clickhouse/__init__.py
pypika/clickhouse/array.py
pypika/clickhouse/condition.py
pypika/clickhouse/dates_and_times.py
pypika/clickhouse/nullable_arg.py
pypika/clickhouse/search_string.py
pypika/clickhouse/type_conversion.py
pypika/tests/__init__.py
pypika/tests/test_aggregate.py
pypika/tests/test_analytic_queries.py
pypika/tests/test_create.py
pypika/tests/test_criterions.py
pypika/tests/test_custom_functions.py
pypika/tests/test_data_types.py
pypika/tests/test_date_math.py
pypika/tests/test_deletes.py
pypika/tests/test_drop.py
pypika/tests/test_formats.py
pypika/tests/test_functions.py
pypika/tests/test_groupby_modifiers.py
pypika/tests/test_immutability.py
pypika/tests/test_inserts.py
pypika/tests/test_internals.py
pypika/tests/test_joins.py
pypika/tests/test_negation.py
pypika/tests/test_parameter.py
pypika/tests/test_pseudocolumns.py
pypika/tests/test_query.py
pypika/tests/test_selects.py
pypika/tests/test_tables.py
pypika/tests/test_terms.py
pypika/tests/test_tuples.py
pypika/tests/test_updates.py
pypika/tests/test_utils.py
pypika/tests/clickhouse/__init__.py
pypika/tests/clickhouse/test_array.py
pypika/tests/clickhouse/test_condition.py
pypika/tests/clickhouse/test_dates_and_times.py
pypika/tests/clickhouse/test_nullable_arg.py
pypika/tests/clickhouse/test_search_string.py
pypika/tests/clickhouse/test_type_conversion.py
pypika/tests/dialects/__init__.py
pypika/tests/dialects/test_clickhouse.py
pypika/tests/dialects/test_mssql.py
pypika/tests/dialects/test_mysql.py
pypika/tests/dialects/test_oracle.py
pypika/tests/dialects/test_postgresql.py
pypika/tests/dialects/test_snowflake.py
pypika/tests/dialects/test_sqllite.py
pypika/tests/dialects/test_vertica.py
pypika_fork-0.51.0.dist-info/METADATA
pypika_fork-0.51.0.dist-info/WHEEL
pypika_fork-0.51.0.dist-info/licenses/LICENSE.txt
pypika_fork-0.51.0.dist-info/RECORD
