Metadata-Version: 2.4
Name: PyPika-fork
Version: 0.51.0
Summary: A SQL query builder API for Python
Project-URL: Homepage, https://github.com/Yolley/pypika
Author-email: Timothy Heys <theys@kayak.com>
License: Apache License Version 2.0
License-File: LICENSE.txt
Keywords: aggregated,analysis,analytics,bi,builder,business,data,database,mapper,mysql,object,oracle,orm,pandas,postgres,psql,pypika,python,query,querybuilder,rdbms,relational,science,sql,vertica
Classifier: Development Status :: 5 - Production/Stable
Classifier: Intended Audience :: Developers
Classifier: License :: OSI Approved :: Apache Software License
Classifier: Operating System :: MacOS :: MacOS X
Classifier: Operating System :: Microsoft :: Windows
Classifier: Operating System :: POSIX
Classifier: Programming Language :: PL/SQL
Classifier: Programming Language :: Python :: 3
Classifier: Topic :: Scientific/Engineering :: Information Analysis
Classifier: Topic :: Scientific/Engineering :: Mathematics
Classifier: Topic :: Software Development :: Libraries :: Python Modules
Requires-Python: >=3.10
